mv_comma_sql/__init__.py
mv_comma_sql/cli.py
mv_comma_sql/type.py
mv_comma_sql-1.0.dist-info/LICENSE
mv_comma_sql-1.0.dist-info/METADATA
mv_comma_sql-1.0.dist-info/WHEEL
mv_comma_sql-1.0.dist-info/entry_points.txt
mv_comma_sql-1.0.dist-info/top_level.txt
mv_comma_sql-1.0.dist-info/RECORD
